[{"code":"140901","subDistrictNameTh":"ภาชี","subDistrictNameEn":"Phachi","subDistrictCode":"1409"},{"code":"140902","subDistrictNameTh":"โคกม่วง","subDistrictNameEn":"Khok Muang","subDistrictCode":"1409"},{"code":"140903","subDistrictNameTh":"ระโสม","subDistrictNameEn":"Rasom","subDistrictCode":"1409"},{"code":"140904","subDistrictNameTh":"หนองน้ำใส","subDistrictNameEn":"Nong Nam Sai","subDistrictCode":"1409"},{"code":"140905","subDistrictNameTh":"ดอนหญ้านาง","subDistrictNameEn":"Don Ya Nang","subDistrictCode":"1409"},{"code":"140906","subDistrictNameTh":"ไผ่ล้อม","subDistrictNameEn":"Phai Lom","subDistrictCode":"1409"},{"code":"140907","subDistrictNameTh":"กระจิว","subDistrictNameEn":"Krachio","subDistrictCode":"1409"},{"code":"140908","subDistrictNameTh":"พระแก้ว","subDistrictNameEn":"Phra Kaeo","subDistrictCode":"1409"}]