[
  {
    "districtCode": 4201,
    "districtNameTh": "เมืองเลย",
    "districtNameEn": "Mueang Loei",
    "provinceCode": "42"
  },
  {
    "districtCode": 4202,
    "districtNameTh": "นาด้วง",
    "districtNameEn": "Na Duang",
    "provinceCode": "42"
  },
  {
    "districtCode": 4203,
    "districtNameTh": "เชียงคาน",
    "districtNameEn": "Chiang Khan",
    "provinceCode": "42"
  },
  {
    "districtCode": 4204,
    "districtNameTh": "ปากชม",
    "districtNameEn": "Pak Chom",
    "provinceCode": "42"
  },
  {
    "districtCode": 4205,
    "districtNameTh": "ด่านซ้าย",
    "districtNameEn": "Dan Sai",
    "provinceCode": "42"
  },
  {
    "districtCode": 4206,
    "districtNameTh": "นาแห้ว",
    "districtNameEn": "Na Haeo",
    "provinceCode": "42"
  },
  {
    "districtCode": 4207,
    "districtNameTh": "ภูเรือ",
    "districtNameEn": "Phu Ruea",
    "provinceCode": "42"
  },
  {
    "districtCode": 4208,
    "districtNameTh": "ท่าลี่",
    "districtNameEn": "Tha Li",
    "provinceCode": "42"
  },
  {
    "districtCode": 4209,
    "districtNameTh": "วังสะพุง",
    "districtNameEn": "Wang Saphung",
    "provinceCode": "42"
  },
  {
    "districtCode": 4210,
    "districtNameTh": "ภูกระดึง",
    "districtNameEn": "Phu Kradueng",
    "provinceCode": "42"
  },
  {
    "districtCode": 4211,
    "districtNameTh": "ภูหลวง",
    "districtNameEn": "Phu Luang",
    "provinceCode": "42"
  },
  {
    "districtCode": 4212,
    "districtNameTh": "ผาขาว",
    "districtNameEn": "Pha  Khao",
    "provinceCode": "42"
  },
  {
    "districtCode": 4213,
    "districtNameTh": "เอราวัณ",
    "districtNameEn": "Erawan",
    "provinceCode": "42"
  },
  {
    "districtCode": 4214,
    "districtNameTh": "หนองหิน",
    "districtNameEn": "Nong Hin",
    "provinceCode": "42"
  }
]
