[
  {
    "districtCode": 7201,
    "districtNameTh": "เมืองสุพรรณบุรี",
    "districtNameEn": "Mueang Saphan Buri",
    "provinceCode": "72"
  },
  {
    "districtCode": 7202,
    "districtNameTh": "เดิมบางนางบวช",
    "districtNameEn": "Doem Bang Nang Buat",
    "provinceCode": "72"
  },
  {
    "districtCode": 7203,
    "districtNameTh": "ด่านช้าง",
    "districtNameEn": "Dan Chang",
    "provinceCode": "72"
  },
  {
    "districtCode": 7204,
    "districtNameTh": "บางปลาม้า",
    "districtNameEn": "Bang Pla Ma",
    "provinceCode": "72"
  },
  {
    "districtCode": 7205,
    "districtNameTh": "ศรีประจันต์",
    "districtNameEn": "Si Prachan",
    "provinceCode": "72"
  },
  {
    "districtCode": 7206,
    "districtNameTh": "ดอนเจดีย์",
    "districtNameEn": "Don Chedi",
    "provinceCode": "72"
  },
  {
    "districtCode": 7207,
    "districtNameTh": "สองพี่น้อง",
    "districtNameEn": "Song Phi Nong",
    "provinceCode": "72"
  },
  {
    "districtCode": 7208,
    "districtNameTh": "สามชุก",
    "districtNameEn": "Sam Chuk",
    "provinceCode": "72"
  },
  {
    "districtCode": 7209,
    "districtNameTh": "อู่ทอง",
    "districtNameEn": "U Thong",
    "provinceCode": "72"
  },
  {
    "districtCode": 7210,
    "districtNameTh": "หนองหญ้าไซ",
    "districtNameEn": "Nong Ya Sai",
    "provinceCode": "72"
  }
]
